LICENSE
MANIFEST.in
README.rst
setup.py
Tinkerer_Localpost.egg-info/PKG-INFO
Tinkerer_Localpost.egg-info/SOURCES.txt
Tinkerer_Localpost.egg-info/dependency_links.txt
Tinkerer_Localpost.egg-info/entry_points.txt
Tinkerer_Localpost.egg-info/requires.txt
Tinkerer_Localpost.egg-info/top_level.txt
localpost/__init__.py
localpost/cmdline.py
localpost/output.py
localpost/server.py