Metadata-Version: 1.1
Name: Tinkerer-Localpost
Version: 0.1.0
Summary: Localhost your Tinkerer blog
Home-page: http://github.com/gisraptor/tinkerer-localpost
Author: Nathan Hawkes
Author-email: gisraptor@gmail.com
License: FreeBSD
Download-URL: https://pypi.python.org/pypi/Tinkerer-Localpost
Platform: any
Classifier: Development Status :: 3 - Alpha
Classifier: Environment :: Console
Classifier: Environment :: Web Environment
Classifier: Intended Audience :: End Users/Desktop
Classifier: Intended Audience :: Developers
Classifier: License :: OSI Approved :: BSD License
Classifier: Operating System :: OS Independent
Classifier: Programming Language :: Python
Classifier: Topic :: Communications
Classifier: Topic :: Internet
Classifier: Topic :: Utilities
